yocho/__init__.py
yocho/rdflib_xtl/__init__.py
yocho/rdflib_xtl/cli.py
yocho.rdflib_xtl-0.3.0.dist-info/entry_points.txt
yocho.rdflib_xtl-0.3.0.dist-info/WHEEL
yocho.rdflib_xtl-0.3.0.dist-info/METADATA
yocho.rdflib_xtl-0.3.0.dist-info/RECORD
