Metadata-Version: 2.1
Name: yocho.rdflib-xtl
Version: 0.3.0
Summary: Extra tools for rdflib
License: CC0-1.0
Author: Iwan Aucamp
Author-email: aucampia@gmail.com
Requires-Python: >=3.6,<4.0
Classifier: License :: CC0 1.0 Universal (CC0 1.0) Public Domain Dedication
Classifier: Programming Language :: Python :: 3
Classifier: Programming Language :: Python :: 3.6
Classifier: Programming Language :: Python :: 3.7
Classifier: Programming Language :: Python :: 3.8
Requires-Dist: owlrl (>=5.2.1,<6.0.0)
Requires-Dist: pyyaml (>=5.3.1,<6.0.0)
Requires-Dist: rdflib (>=5.0.0,<6.0.0)
Requires-Dist: rdflib-jsonld (>=0.5.0,<0.6.0)
Requires-Dist: requests (>=2.24.0,<3.0.0)
